{
    "AX": {
        "error": 0.007447944157450137,
        "error_type": "SEM",
        "filter_outliers_dict": {
            "filter_outliers": true,
            "iterations": 1,
            "std_devs": 3,
            "use_iqr_filtering": false,
            "use_standard_deviation_filtering": false
        },
        "fit": "average",
        "fn": 60,
        "include_baseline_error": false,
        "n": 60,
        "outlier_excluded": [],
        "reviewed": true,
        "user_excluded": [],
        "value": -0.09050479835520188
    },
    "CDD": {
        "error": 3.273274687932891e-05,
        "error_type": "SEM",
        "filter_outliers_dict": {
            "filter_outliers": true,
            "iterations": 1,
            "std_devs": 10,
            "use_iqr_filtering": false,
            "use_standard_deviation_filtering": false
        },
        "fit": "average",
        "fn": 60,
        "include_baseline_error": false,
        "n": 60,
        "outlier_excluded": [],
        "reviewed": true,
        "user_excluded": [],
        "value": 0.00037149023725457177
    },
    "H1": {
        "error": 0.005798789297001282,
        "error_type": "SEM",
        "filter_outliers_dict": {
            "filter_outliers": true,
            "iterations": 1,
            "std_devs": 3,
            "use_iqr_filtering": false,
            "use_standard_deviation_filtering": false
        },
        "fit": "average",
        "fn": 60,
        "include_baseline_error": false,
        "n": 60,
        "outlier_excluded": [],
        "reviewed": true,
        "user_excluded": [],
        "value": 0.05774442500745257
    },
    "H2": {
        "error": 0.002813897946922825,
        "error_type": "SEM",
        "filter_outliers_dict": {
            "filter_outliers": true,
            "iterations": 1,
            "std_devs": 3,
            "use_iqr_filtering": false,
            "use_standard_deviation_filtering": false
        },
        "fit": "average",
        "fn": 60,
        "include_baseline_error": false,
        "n": 60,
        "outlier_excluded": [],
        "reviewed": true,
        "user_excluded": [],
        "value": 0.008278432703688547
    },
    "L1": {
        "error": 0.0031088607387656396,
        "error_type": "SEM",
        "filter_outliers_dict": {
            "filter_outliers": true,
            "iterations": 1,
            "std_devs": 3,
            "use_iqr_filtering": false,
            "use_standard_deviation_filtering": false
        },
        "fit": "average",
        "fn": 60,
        "include_baseline_error": false,
        "n": 60,
        "outlier_excluded": [],
        "reviewed": true,
        "user_excluded": [],
        "value": 0.08018879508599638
    },
    "L2": {
        "error": 0.0054660448890984726,
        "error_type": "SEM",
        "filter_outliers_dict": {
            "filter_outliers": true,
            "iterations": 1,
            "std_devs": 2
        },
        "fit": "average",
        "value": -0.06720588881596498
    }
}